aiosenz/__init__.py
aiosenz/account.py
aiosenz/api.py
aiosenz/auth.py
aiosenz/py.typed
aiosenz/thermostat.py
aiosenz/typing.py
aiosenz-1.0.0.dist-info/COPYING
aiosenz-1.0.0.dist-info/METADATA
aiosenz-1.0.0.dist-info/WHEEL
aiosenz-1.0.0.dist-info/top_level.txt
aiosenz-1.0.0.dist-info/RECORD
