Metadata-Version: 2.1
Name: aiosenz
Version: 1.0.0
Summary: Async Typed Python package for the nVent RAYCHEM SENZ RestAPI
Home-page: https://github.com/milanmeu/aiosenz
Author: Milan Meulemans
Author-email: milan.meulemans@live.be
Maintainer: Milan Meulemans
Maintainer-email: milan.meulemans@live.be
License: LGPLv3+
Project-URL: Say Thanks!, https://saythanks.io/to/milan.meulemans@live.be
Project-URL: Bug Tracker, https://github.com/milanmeu/aiosenz/issues
Project-URL: Source Code, https://github.com/milanmeu/aiosenz
Project-URL: Documentation, https://github.com/milanmeu/aiosenz/blob/main/README.md
Keywords: nvent,raychem,senz,wifi,api,restapi,oauth2
Platform: UNKNOWN
Classifier: Programming Language :: Python :: 3
Classifier: License :: OSI Approved :: GNU Lesser General Public License v3 or later (LGPLv3+)
Classifier: Operating System :: OS Independent
Requires-Python: >=3.8
License-File: COPYING
Requires-Dist: httpx
Requires-Dist: authlib
